[
    {
        "id": "CUURX200SA0",
        "realtime_start": "2024-12-01",
        "realtime_end": "2024-12-01",
        "title": "Consumer Price Index for All Urban Consumers: All Items in Midwest - Size Class B/C",
        "observation_start": "1996-12-01",
        "observation_end": "2024-10-01",
        "frequency": "Monthly",
        "frequency_short": "M",
        "units": "Index Dec 1996=100",
        "units_short": "Index Dec 1996=100",
        "seasonal_adjustment": "Not Seasonally Adjusted",
        "seasonal_adjustment_short": "NSA",
        "last_updated": "2024-11-13 07:44:09-06",
        "popularity": 4,
        "group_popularity": 5
    },
    {
        "id": "CUURX200SA0E",
        "realtime_start": "2024-12-01",
        "realtime_end": "2024-12-01",
        "title": "Consumer Price Index for All Urban Consumers: Energy in Midwest - Size Class B/C",
        "observation_start": "1997-12-01",
        "observation_end": "2024-10-01",
        "frequency": "Monthly",
        "frequency_short": "M",
        "units": "Index Dec 1997=100",
        "units_short": "Index Dec 1997=100",
        "seasonal_adjustment": "Not Seasonally Adjusted",
        "seasonal_adjustment_short": "NSA",
        "last_updated": "2024-11-13 07:44:17-06",
        "popularity": 1,
        "group_popularity": 1
    },
    {
        "id": "CUURX200SA0L1E",
        "realtime_start": "2024-12-01",
        "realtime_end": "2024-12-01",
        "title": "Consumer Price Index for All Urban Consumers: All Items Less Food and Energy in Midwest - Size Class B/C",
        "observation_start": "1997-12-01",
        "observation_end": "2024-10-01",
        "frequency": "Monthly",
        "frequency_short": "M",
        "units": "Index Dec 1997=100",
        "units_short": "Index Dec 1997=100",
        "seasonal_adjustment": "Not Seasonally Adjusted",
        "seasonal_adjustment_short": "NSA",
        "last_updated": "2024-11-13 07:44:17-06",
        "popularity": 1,
        "group_popularity": 1
    },
    {
        "id": "CUURX200SA0L2",
        "realtime_start": "2024-12-01",
        "realtime_end": "2024-12-01",
        "title": "Consumer Price Index for All Urban Consumers: All Items Less Shelter in Midwest - Size Class B/C",
        "observation_start": "1997-12-01",
        "observation_end": "2024-10-01",
        "frequency": "Monthly",
        "frequency_short": "M",
        "units": "Index Dec 1997=100",
        "units_short": "Index Dec 1997=100",
        "seasonal_adjustment": "Not Seasonally Adjusted",
        "seasonal_adjustment_short": "NSA",
        "last_updated": "2024-11-13 07:44:17-06",
        "popularity": 1,
        "group_popularity": 1
    },
    {
        "id": "CUURX200SA0L5",
        "realtime_start": "2024-12-01",
        "realtime_end": "2024-12-01",
        "title": "Consumer Price Index for All Urban Consumers: All Items Less Medical Care in Midwest - Size Class B/C",
        "observation_start": "1997-12-01",
        "observation_end": "2024-10-01",
        "frequency": "Monthly",
        "frequency_short": "M",
        "units": "Index Dec 1997=100",
        "units_short": "Index Dec 1997=100",
        "seasonal_adjustment": "Not Seasonally Adjusted",
        "seasonal_adjustment_short": "NSA",
        "last_updated": "2024-11-13 07:44:17-06",
        "popularity": 1,
        "group_popularity": 1
    },
    {
        "id": "CUURX200SA0LE",
        "realtime_start": "2024-12-01",
        "realtime_end": "2024-12-01",
        "title": "Consumer Price Index for All Urban Consumers: All Items Less Energy in Midwest - Size Class B/C",
        "observation_start": "1997-12-01",
        "observation_end": "2024-10-01",
        "frequency": "Monthly",
        "frequency_short": "M",
        "units": "Index Dec 1997=100",
        "units_short": "Index Dec 1997=100",
        "seasonal_adjustment": "Not Seasonally Adjusted",
        "seasonal_adjustment_short": "NSA",
        "last_updated": "2024-11-13 07:43:33-06",
        "popularity": 1,
        "group_popularity": 1
    },
    {
        "id": "CUURX200SAA",
        "realtime_start": "2024-12-01",
        "realtime_end": "2024-12-01",
        "title": "Consumer Price Index for All Urban Consumers: Apparel in Midwest - Size Class B/C",
        "observation_start": "1997-12-01",
        "observation_end": "2024-10-01",
        "frequency": "Monthly",
        "frequency_short": "M",
        "units": "Index Dec 1997=100",
        "units_short": "Index Dec 1997=100",
        "seasonal_adjustment": "Not Seasonally Adjusted",
        "seasonal_adjustment_short": "NSA",
        "last_updated": "2024-11-13 07:45:14-06",
        "popularity": 0,
        "group_popularity": 0
    },
    {
        "id": "CUURX200SAC",
        "realtime_start": "2024-12-01",
        "realtime_end": "2024-12-01",
        "title": "Consumer Price Index for All Urban Consumers: Commodities in Midwest - Size Class B/C",
        "observation_start": "1997-12-01",
        "observation_end": "2024-10-01",
        "frequency": "Monthly",
        "frequency_short": "M",
        "units": "Index Dec 1997=100",
        "units_short": "Index Dec 1997=100",
        "seasonal_adjustment": "Not Seasonally Adjusted",
        "seasonal_adjustment_short": "NSA",
        "last_updated": "2024-11-13 07:45:14-06",
        "popularity": 0,
        "group_popularity": 0
    },
    {
        "id": "CUURX200SACL1",
        "realtime_start": "2024-12-01",
        "realtime_end": "2024-12-01",
        "title": "Consumer Price Index for All Urban Consumers: Commodities Less Food in Midwest - Size Class B/C",
        "observation_start": "1997-12-01",
        "observation_end": "2024-10-01",
        "frequency": "Monthly",
        "frequency_short": "M",
        "units": "Index Dec 1997=100",
        "units_short": "Index Dec 1997=100",
        "seasonal_adjustment": "Not Seasonally Adjusted",
        "seasonal_adjustment_short": "NSA",
        "last_updated": "2024-11-13 07:45:14-06",
        "popularity": 0,
        "group_popularity": 0
    },
    {
        "id": "CUURX200SACL11",
        "realtime_start": "2024-12-01",
        "realtime_end": "2024-12-01",
        "title": "Consumer Price Index for All Urban Consumers: Commodities Less Food and Beverages in Midwest - Size Class B/C",
        "observation_start": "1997-12-01",
        "observation_end": "2024-10-01",
        "frequency": "Monthly",
        "frequency_short": "M",
        "units": "Index Dec 1997=100",
        "units_short": "Index Dec 1997=100",
        "seasonal_adjustment": "Not Seasonally Adjusted",
        "seasonal_adjustment_short": "NSA",
        "last_updated": "2024-11-13 07:45:14-06",
        "popularity": 0,
        "group_popularity": 0
    },
    {
        "id": "CUURX200SAD",
        "realtime_start": "2024-12-01",
        "realtime_end": "2024-12-01",
        "title": "Consumer Price Index for All Urban Consumers: Durables in Midwest - Size Class B/C",
        "observation_start": "1997-12-01",
        "observation_end": "2024-10-01",
        "frequency": "Monthly",
        "frequency_short": "M",
        "units": "Index Dec 1997=100",
        "units_short": "Index Dec 1997=100",
        "seasonal_adjustment": "Not Seasonally Adjusted",
        "seasonal_adjustment_short": "NSA",
        "last_updated": "2024-11-13 07:45:14-06",
        "popularity": 0,
        "group_popularity": 0
    },
    {
        "id": "CUURX200SAE",
        "realtime_start": "2024-12-01",
        "realtime_end": "2024-12-01",
        "title": "Consumer Price Index for All Urban Consumers: Education and Communication in Midwest - Size Class B/C",
        "observation_start": "1997-12-01",
        "observation_end": "2024-10-01",
        "frequency": "Monthly",
        "frequency_short": "M",
        "units": "Index Dec 1997=100",
        "units_short": "Index Dec 1997=100",
        "seasonal_adjustment": "Not Seasonally Adjusted",
        "seasonal_adjustment_short": "NSA",
        "last_updated": "2024-11-13 07:45:14-06",
        "popularity": 0,
        "group_popularity": 1
    },
    {
        "id": "CUURX200SAEC",
        "realtime_start": "2024-12-01",
        "realtime_end": "2024-12-01",
        "title": "Consumer Price Index for All Urban Consumers: Education and Communication Commodities in Midwest - Size Class B/C",
        "observation_start": "2009-12-01",
        "observation_end": "2024-10-01",
        "frequency": "Monthly",
        "frequency_short": "M",
        "units": "Index Dec 2009=100",
        "units_short": "Index Dec 2009=100",
        "seasonal_adjustment": "Not Seasonally Adjusted",
        "seasonal_adjustment_short": "NSA",
        "last_updated": "2024-11-13 07:45:14-06",
        "popularity": 0,
        "group_popularity": 0
    },
    {
        "id": "CUURX200SAES",
        "realtime_start": "2024-12-01",
        "realtime_end": "2024-12-01",
        "title": "Consumer Price Index for All Urban Consumers: Education and Communication Services in Midwest - Size Class B/C",
        "observation_start": "2009-12-01",
        "observation_end": "2024-10-01",
        "frequency": "Monthly",
        "frequency_short": "M",
        "units": "Index Dec 2009=100",
        "units_short": "Index Dec 2009=100",
        "seasonal_adjustment": "Not Seasonally Adjusted",
        "seasonal_adjustment_short": "NSA",
        "last_updated": "2024-11-13 07:45:13-06",
        "popularity": 0,
        "group_popularity": 0
    },
    {
        "id": "CUURX200SAF",
        "realtime_start": "2024-12-01",
        "realtime_end": "2024-12-01",
        "title": "Consumer Price Index for All Urban Consumers: Food and Beverages in Midwest - Size Class B/C",
        "observation_start": "1997-12-01",
        "observation_end": "2024-10-01",
        "frequency": "Monthly",
        "frequency_short": "M",
        "units": "Index Dec 1997=100",
        "units_short": "Index Dec 1997=100",
        "seasonal_adjustment": "Not Seasonally Adjusted",
        "seasonal_adjustment_short": "NSA",
        "last_updated": "2024-11-13 07:45:13-06",
        "popularity": 0,
        "group_popularity": 1
    },
    {
        "id": "CUURX200SAF1",
        "realtime_start": "2024-12-01",
        "realtime_end": "2024-12-01",
        "title": "Consumer Price Index for All Urban Consumers: Food in Midwest - Size Class B/C",
        "observation_start": "1997-12-01",
        "observation_end": "2024-10-01",
        "frequency": "Monthly",
        "frequency_short": "M",
        "units": "Index Dec 1997=100",
        "units_short": "Index Dec 1997=100",
        "seasonal_adjustment": "Not Seasonally Adjusted",
        "seasonal_adjustment_short": "NSA",
        "last_updated": "2024-11-13 07:45:13-06",
        "popularity": 0,
        "group_popularity": 1
    },
    {
        "id": "CUURX200SAF11",
        "realtime_start": "2024-12-01",
        "realtime_end": "2024-12-01",
        "title": "Consumer Price Index for All Urban Consumers: Food at Home in Midwest - Size Class B/C",
        "observation_start": "1997-12-01",
        "observation_end": "2024-10-01",
        "frequency": "Monthly",
        "frequency_short": "M",
        "units": "Index Dec 1997=100",
        "units_short": "Index Dec 1997=100",
        "seasonal_adjustment": "Not Seasonally Adjusted",
        "seasonal_adjustment_short": "NSA",
        "last_updated": "2024-11-13 07:44:17-06",
        "popularity": 1,
        "group_popularity": 1
    },
    {
        "id": "CUURX200SAF116",
        "realtime_start": "2024-12-01",
        "realtime_end": "2024-12-01",
        "title": "Consumer Price Index for All Urban Consumers: Alcoholic Beverages in Midwest - Size Class B/C",
        "observation_start": "1997-12-01",
        "observation_end": "2024-10-01",
        "frequency": "Monthly",
        "frequency_short": "M",
        "units": "Index Dec 1997=100",
        "units_short": "Index Dec 1997=100",
        "seasonal_adjustment": "Not Seasonally Adjusted",
        "seasonal_adjustment_short": "NSA",
        "last_updated": "2024-11-13 07:44:17-06",
        "popularity": 1,
        "group_popularity": 1
    },
    {
        "id": "CUURX200SAG",
        "realtime_start": "2024-12-01",
        "realtime_end": "2024-12-01",
        "title": "Consumer Price Index for All Urban Consumers: Other Goods and Services in Midwest - Size Class B/C",
        "observation_start": "1997-12-01",
        "observation_end": "2024-10-01",
        "frequency": "Monthly",
        "frequency_short": "M",
        "units": "Index Dec 1997=100",
        "units_short": "Index Dec 1997=100",
        "seasonal_adjustment": "Not Seasonally Adjusted",
        "seasonal_adjustment_short": "NSA",
        "last_updated": "2024-11-13 07:45:13-06",
        "popularity": 0,
        "group_popularity": 0
    },
    {
        "id": "CUURX200SAGC",
        "realtime_start": "2024-12-01",
        "realtime_end": "2024-12-01",
        "title": "Consumer Price Index for All Urban Consumers: Other Goods in Midwest - Size Class B/C",
        "observation_start": "2009-12-01",
        "observation_end": "2024-10-01",
        "frequency": "Monthly",
        "frequency_short": "M",
        "units": "Index Dec 2009=100",
        "units_short": "Index Dec 2009=100",
        "seasonal_adjustment": "Not Seasonally Adjusted",
        "seasonal_adjustment_short": "NSA",
        "last_updated": "2024-11-13 07:45:13-06",
        "popularity": 0,
        "group_popularity": 0
    },
    {
        "id": "CUURX200SAGS",
        "realtime_start": "2024-12-01",
        "realtime_end": "2024-12-01",
        "title": "Consumer Price Index for All Urban Consumers: Other Personal Services in Midwest - Size Class B/C",
        "observation_start": "2009-12-01",
        "observation_end": "2024-10-01",
        "frequency": "Monthly",
        "frequency_short": "M",
        "units": "Index Dec 2009=100",
        "units_short": "Index Dec 2009=100",
        "seasonal_adjustment": "Not Seasonally Adjusted",
        "seasonal_adjustment_short": "NSA",
        "last_updated": "2024-11-13 07:45:13-06",
        "popularity": 0,
        "group_popularity": 0
    },
    {
        "id": "CUURX200SAH",
        "realtime_start": "2024-12-01",
        "realtime_end": "2024-12-01",
        "title": "Consumer Price Index for All Urban Consumers: Housing in Midwest - Size Class B/C",
        "observation_start": "1997-12-01",
        "observation_end": "2024-10-01",
        "frequency": "Monthly",
        "frequency_short": "M",
        "units": "Index Dec 1997=100",
        "units_short": "Index Dec 1997=100",
        "seasonal_adjustment": "Not Seasonally Adjusted",
        "seasonal_adjustment_short": "NSA",
        "last_updated": "2024-11-13 07:44:17-06",
        "popularity": 1,
        "group_popularity": 1
    },
    {
        "id": "CUURX200SAH1",
        "realtime_start": "2024-12-01",
        "realtime_end": "2024-12-01",
        "title": "Consumer Price Index for All Urban Consumers: Shelter in Midwest - Size Class B/C",
        "observation_start": "1997-12-01",
        "observation_end": "2024-10-01",
        "frequency": "Monthly",
        "frequency_short": "M",
        "units": "Index Dec 1997=100",
        "units_short": "Index Dec 1997=100",
        "seasonal_adjustment": "Not Seasonally Adjusted",
        "seasonal_adjustment_short": "NSA",
        "last_updated": "2024-11-13 07:44:16-06",
        "popularity": 1,
        "group_popularity": 1
    },
    {
        "id": "CUURX200SAH2",
        "realtime_start": "2024-12-01",
        "realtime_end": "2024-12-01",
        "title": "Consumer Price Index for All Urban Consumers: Fuels and Utilities in Midwest - Size Class B/C",
        "observation_start": "1997-12-01",
        "observation_end": "2024-10-01",
        "frequency": "Monthly",
        "frequency_short": "M",
        "units": "Index Dec 1997=100",
        "units_short": "Index Dec 1997=100",
        "seasonal_adjustment": "Not Seasonally Adjusted",
        "seasonal_adjustment_short": "NSA",
        "last_updated": "2024-11-13 07:44:16-06",
        "popularity": 1,
        "group_popularity": 1
    },
    {
        "id": "CUURX200SAH21",
        "realtime_start": "2024-12-01",
        "realtime_end": "2024-12-01",
        "title": "Consumer Price Index for All Urban Consumers: Household Energy in Midwest - Size Class B/C",
        "observation_start": "1997-12-01",
        "observation_end": "2024-10-01",
        "frequency": "Monthly",
        "frequency_short": "M",
        "units": "Index Dec 1997=100",
        "units_short": "Index Dec 1997=100",
        "seasonal_adjustment": "Not Seasonally Adjusted",
        "seasonal_adjustment_short": "NSA",
        "last_updated": "2024-11-13 07:45:13-06",
        "popularity": 0,
        "group_popularity": 0
    },
    {
        "id": "CUURX200SAH3",
        "realtime_start": "2024-12-01",
        "realtime_end": "2024-12-01",
        "title": "Consumer Price Index for All Urban Consumers: Household Furnishings and Operations in Midwest - Size Class B/C",
        "observation_start": "1997-12-01",
        "observation_end": "2024-10-01",
        "frequency": "Monthly",
        "frequency_short": "M",
        "units": "Index Dec 1997=100",
        "units_short": "Index Dec 1997=100",
        "seasonal_adjustment": "Not Seasonally Adjusted",
        "seasonal_adjustment_short": "NSA",
        "last_updated": "2024-11-13 07:45:13-06",
        "popularity": 0,
        "group_popularity": 0
    },
    {
        "id": "CUURX200SAH31",
        "realtime_start": "2024-12-01",
        "realtime_end": "2024-12-01",
        "title": "Consumer Price Index for All Urban Consumers: Household Furnishings and Supplies in Midwest - Size Class B/C",
        "observation_start": "2009-12-01",
        "observation_end": "2024-10-01",
        "frequency": "Monthly",
        "frequency_short": "M",
        "units": "Index Dec 2009=100",
        "units_short": "Index Dec 2009=100",
        "seasonal_adjustment": "Not Seasonally Adjusted",
        "seasonal_adjustment_short": "NSA",
        "last_updated": "2024-11-13 07:44:16-06",
        "popularity": 1,
        "group_popularity": 1
    },
    {
        "id": "CUURX200SAM",
        "realtime_start": "2024-12-01",
        "realtime_end": "2024-12-01",
        "title": "Consumer Price Index for All Urban Consumers: Medical Care in Midwest - Size Class B/C",
        "observation_start": "1997-12-01",
        "observation_end": "2024-10-01",
        "frequency": "Monthly",
        "frequency_short": "M",
        "units": "Index Dec 1997=100",
        "units_short": "Index Dec 1997=100",
        "seasonal_adjustment": "Not Seasonally Adjusted",
        "seasonal_adjustment_short": "NSA",
        "last_updated": "2024-11-13 07:44:16-06",
        "popularity": 1,
        "group_popularity": 1
    },
    {
        "id": "CUURX200SAN",
        "realtime_start": "2024-12-01",
        "realtime_end": "2024-12-01",
        "title": "Consumer Price Index for All Urban Consumers: Nondurables in Midwest - Size Class B/C",
        "observation_start": "1997-12-01",
        "observation_end": "2024-10-01",
        "frequency": "Monthly",
        "frequency_short": "M",
        "units": "Index Dec 1997=100",
        "units_short": "Index Dec 1997=100",
        "seasonal_adjustment": "Not Seasonally Adjusted",
        "seasonal_adjustment_short": "NSA",
        "last_updated": "2024-11-13 07:45:13-06",
        "popularity": 0,
        "group_popularity": 0
    },
    {
        "id": "CUURX200SANL1",
        "realtime_start": "2024-12-01",
        "realtime_end": "2024-12-01",
        "title": "Consumer Price Index for All Urban Consumers: Nondurables Less Food in Midwest - Size Class B/C",
        "observation_start": "1997-12-01",
        "observation_end": "2024-10-01",
        "frequency": "Monthly",
        "frequency_short": "M",
        "units": "Index Dec 1997=100",
        "units_short": "Index Dec 1997=100",
        "seasonal_adjustment": "Not Seasonally Adjusted",
        "seasonal_adjustment_short": "NSA",
        "last_updated": "2024-11-13 07:44:16-06",
        "popularity": 1,
        "group_popularity": 1
    },
    {
        "id": "CUURX200SANL11",
        "realtime_start": "2024-12-01",
        "realtime_end": "2024-12-01",
        "title": "Consumer Price Index for All Urban Consumers: Nondurables Less Food and Beverages in Midwest - Size Class B/C",
        "observation_start": "1997-12-01",
        "observation_end": "2024-10-01",
        "frequency": "Monthly",
        "frequency_short": "M",
        "units": "Index Dec 1997=100",
        "units_short": "Index Dec 1997=100",
        "seasonal_adjustment": "Not Seasonally Adjusted",
        "seasonal_adjustment_short": "NSA",
        "last_updated": "2024-11-13 07:45:13-06",
        "popularity": 0,
        "group_popularity": 0
    },
    {
        "id": "CUURX200SAR",
        "realtime_start": "2024-12-01",
        "realtime_end": "2024-12-01",
        "title": "Consumer Price Index for All Urban Consumers: Recreation in Midwest - Size Class B/C",
        "observation_start": "1997-12-01",
        "observation_end": "2024-10-01",
        "frequency": "Monthly",
        "frequency_short": "M",
        "units": "Index Dec 1997=100",
        "units_short": "Index Dec 1997=100",
        "seasonal_adjustment": "Not Seasonally Adjusted",
        "seasonal_adjustment_short": "NSA",
        "last_updated": "2024-11-13 07:44:16-06",
        "popularity": 1,
        "group_popularity": 1
    },
    {
        "id": "CUURX200SAS",
        "realtime_start": "2024-12-01",
        "realtime_end": "2024-12-01",
        "title": "Consumer Price Index for All Urban Consumers: Services in Midwest - Size Class B/C",
        "observation_start": "1997-12-01",
        "observation_end": "2024-10-01",
        "frequency": "Monthly",
        "frequency_short": "M",
        "units": "Index Dec 1997=100",
        "units_short": "Index Dec 1997=100",
        "seasonal_adjustment": "Not Seasonally Adjusted",
        "seasonal_adjustment_short": "NSA",
        "last_updated": "2024-11-13 07:45:13-06",
        "popularity": 0,
        "group_popularity": 0
    },
    {
        "id": "CUURX200SASL2RS",
        "realtime_start": "2024-12-01",
        "realtime_end": "2024-12-01",
        "title": "Consumer Price Index for All Urban Consumers: Services Less Rent of Shelter in Midwest - Size Class B/C",
        "observation_start": "1997-12-01",
        "observation_end": "2024-10-01",
        "frequency": "Monthly",
        "frequency_short": "M",
        "units": "Index Dec 1997=100",
        "units_short": "Index Dec 1997=100",
        "seasonal_adjustment": "Not Seasonally Adjusted",
        "seasonal_adjustment_short": "NSA",
        "last_updated": "2024-11-13 07:45:13-06",
        "popularity": 0,
        "group_popularity": 1
    },
    {
        "id": "CUURX200SASL5",
        "realtime_start": "2024-12-01",
        "realtime_end": "2024-12-01",
        "title": "Consumer Price Index for All Urban Consumers: Services Less Medical Care Services in Midwest - Size Class B/C",
        "observation_start": "1997-12-01",
        "observation_end": "2024-10-01",
        "frequency": "Monthly",
        "frequency_short": "M",
        "units": "Index Dec 1997=100",
        "units_short": "Index Dec 1997=100",
        "seasonal_adjustment": "Not Seasonally Adjusted",
        "seasonal_adjustment_short": "NSA",
        "last_updated": "2024-11-13 07:44:16-06",
        "popularity": 1,
        "group_popularity": 1
    },
    {
        "id": "CUURX200SAT",
        "realtime_start": "2024-12-01",
        "realtime_end": "2024-12-01",
        "title": "Consumer Price Index for All Urban Consumers: Transportation in Midwest - Size Class B/C",
        "observation_start": "1997-12-01",
        "observation_end": "2024-10-01",
        "frequency": "Monthly",
        "frequency_short": "M",
        "units": "Index Dec 1997=100",
        "units_short": "Index Dec 1997=100",
        "seasonal_adjustment": "Not Seasonally Adjusted",
        "seasonal_adjustment_short": "NSA",
        "last_updated": "2024-11-13 07:45:13-06",
        "popularity": 0,
        "group_popularity": 0
    },
    {
        "id": "CUURX200SAT1",
        "realtime_start": "2024-12-01",
        "realtime_end": "2024-12-01",
        "title": "Consumer Price Index for All Urban Consumers: Private Transportation in Midwest - Size Class B/C",
        "observation_start": "1997-12-01",
        "observation_end": "2024-10-01",
        "frequency": "Monthly",
        "frequency_short": "M",
        "units": "Index Dec 1997=100",
        "units_short": "Index Dec 1997=100",
        "seasonal_adjustment": "Not Seasonally Adjusted",
        "seasonal_adjustment_short": "NSA",
        "last_updated": "2024-11-13 07:45:13-06",
        "popularity": 0,
        "group_popularity": 0
    },
    {
        "id": "CUURX200SATCLTB",
        "realtime_start": "2024-12-01",
        "realtime_end": "2024-12-01",
        "title": "Consumer Price Index for All Urban Consumers: Transportation Commodities Less Motor Fuel in Midwest - Size Class B/C",
        "observation_start": "2009-12-01",
        "observation_end": "2024-10-01",
        "frequency": "Monthly",
        "frequency_short": "M",
        "units": "Index Dec 2009=100",
        "units_short": "Index Dec 2009=100",
        "seasonal_adjustment": "Not Seasonally Adjusted",
        "seasonal_adjustment_short": "NSA",
        "last_updated": "2024-11-13 07:44:16-06",
        "popularity": 1,
        "group_popularity": 1
    },
    {
        "id": "CUURX200SEFV",
        "realtime_start": "2024-12-01",
        "realtime_end": "2024-12-01",
        "title": "Consumer Price Index for All Urban Consumers: Food Away from Home in Midwest - Size Class B/C",
        "observation_start": "1997-12-01",
        "observation_end": "2024-10-01",
        "frequency": "Monthly",
        "frequency_short": "M",
        "units": "Index Dec 1997=100",
        "units_short": "Index Dec 1997=100",
        "seasonal_adjustment": "Not Seasonally Adjusted",
        "seasonal_adjustment_short": "NSA",
        "last_updated": "2024-11-13 07:45:13-06",
        "popularity": 0,
        "group_popularity": 0
    },
    {
        "id": "CUURX200SEHA",
        "realtime_start": "2024-12-01",
        "realtime_end": "2024-12-01",
        "title": "Consumer Price Index for All Urban Consumers: Rent of Primary Residence in Midwest - Size Class B/C",
        "observation_start": "1997-12-01",
        "observation_end": "2024-10-01",
        "frequency": "Monthly",
        "frequency_short": "M",
        "units": "Index Dec 1997=100",
        "units_short": "Index Dec 1997=100",
        "seasonal_adjustment": "Not Seasonally Adjusted",
        "seasonal_adjustment_short": "NSA",
        "last_updated": "2024-11-13 07:44:16-06",
        "popularity": 1,
        "group_popularity": 1
    },
    {
        "id": "CUURX200SEHC",
        "realtime_start": "2024-12-01",
        "realtime_end": "2024-12-01",
        "title": "Consumer Price Index for All Urban Consumers: Owners' Equivalent Rent of Residences in Midwest - Size Class B/C",
        "observation_start": "1997-12-01",
        "observation_end": "2024-10-01",
        "frequency": "Monthly",
        "frequency_short": "M",
        "units": "Index Dec 1997=100",
        "units_short": "Index Dec 1997=100",
        "seasonal_adjustment": "Not Seasonally Adjusted",
        "seasonal_adjustment_short": "NSA",
        "last_updated": "2024-11-13 07:44:16-06",
        "popularity": 1,
        "group_popularity": 1
    },
    {
        "id": "CUURX200SEHC01",
        "realtime_start": "2024-12-01",
        "realtime_end": "2024-12-01",
        "title": "Consumer Price Index for All Urban Consumers: Owners' Equivalent Rent of Primary Residence in Midwest - Size Class B/C",
        "observation_start": "1997-12-01",
        "observation_end": "2024-10-01",
        "frequency": "Monthly",
        "frequency_short": "M",
        "units": "Index Dec 1997=100",
        "units_short": "Index Dec 1997=100",
        "seasonal_adjustment": "Not Seasonally Adjusted",
        "seasonal_adjustment_short": "NSA",
        "last_updated": "2024-11-13 07:45:12-06",
        "popularity": 0,
        "group_popularity": 0
    },
    {
        "id": "CUURX200SEHF",
        "realtime_start": "2024-12-01",
        "realtime_end": "2024-12-01",
        "title": "Consumer Price Index for All Urban Consumers: Energy Services in Midwest - Size Class B/C",
        "observation_start": "1997-12-01",
        "observation_end": "2024-10-01",
        "frequency": "Monthly",
        "frequency_short": "M",
        "units": "Index Dec 1997=100",
        "units_short": "Index Dec 1997=100",
        "seasonal_adjustment": "Not Seasonally Adjusted",
        "seasonal_adjustment_short": "NSA",
        "last_updated": "2024-11-13 07:45:12-06",
        "popularity": 0,
        "group_popularity": 0
    },
    {
        "id": "CUURX200SEHF01",
        "realtime_start": "2024-12-01",
        "realtime_end": "2024-12-01",
        "title": "Consumer Price Index for All Urban Consumers: Electricity in Midwest - Size Class B/C",
        "observation_start": "1997-12-01",
        "observation_end": "2024-10-01",
        "frequency": "Monthly",
        "frequency_short": "M",
        "units": "Index Dec 1997=100",
        "units_short": "Index Dec 1997=100",
        "seasonal_adjustment": "Not Seasonally Adjusted",
        "seasonal_adjustment_short": "NSA",
        "last_updated": "2024-11-13 07:45:12-06",
        "popularity": 0,
        "group_popularity": 1
    },
    {
        "id": "CUURX200SEHF02",
        "realtime_start": "2024-12-01",
        "realtime_end": "2024-12-01",
        "title": "Consumer Price Index for All Urban Consumers: Utility (Piped) Gas Service in Midwest - Size Class B/C",
        "observation_start": "1997-12-01",
        "observation_end": "2024-10-01",
        "frequency": "Monthly",
        "frequency_short": "M",
        "units": "Index Dec 1997=100",
        "units_short": "Index Dec 1997=100",
        "seasonal_adjustment": "Not Seasonally Adjusted",
        "seasonal_adjustment_short": "NSA",
        "last_updated": "2024-11-13 07:45:12-06",
        "popularity": 0,
        "group_popularity": 0
    },
    {
        "id": "CUURX200SETB",
        "realtime_start": "2024-12-01",
        "realtime_end": "2024-12-01",
        "title": "Consumer Price Index for All Urban Consumers: Motor Fuel in Midwest - Size Class B/C",
        "observation_start": "1997-12-01",
        "observation_end": "2024-10-01",
        "frequency": "Monthly",
        "frequency_short": "M",
        "units": "Index Dec 1997=100",
        "units_short": "Index Dec 1997=100",
        "seasonal_adjustment": "Not Seasonally Adjusted",
        "seasonal_adjustment_short": "NSA",
        "last_updated": "2024-11-13 07:45:12-06",
        "popularity": 0,
        "group_popularity": 1
    },
    {
        "id": "CUURX200SETB01",
        "realtime_start": "2024-12-01",
        "realtime_end": "2024-12-01",
        "title": "Consumer Price Index for All Urban Consumers: Gasoline (All Types) in Midwest - Size Class B/C",
        "observation_start": "1997-12-01",
        "observation_end": "2024-10-01",
        "frequency": "Monthly",
        "frequency_short": "M",
        "units": "Index Dec 1997=100",
        "units_short": "Index Dec 1997=100",
        "seasonal_adjustment": "Not Seasonally Adjusted",
        "seasonal_adjustment_short": "NSA",
        "last_updated": "2024-11-13 07:45:12-06",
        "popularity": 0,
        "group_popularity": 1
    },
    {
        "id": "CUURX200SS47014",
        "realtime_start": "2024-12-01",
        "realtime_end": "2024-12-01",
        "title": "Consumer Price Index for All Urban Consumers: Gasoline, Unleaded Regular in Midwest - Size Class B/C",
        "observation_start": "1997-12-01",
        "observation_end": "2024-10-01",
        "frequency": "Monthly",
        "frequency_short": "M",
        "units": "Index Dec 1997=100",
        "units_short": "Index Dec 1997=100",
        "seasonal_adjustment": "Not Seasonally Adjusted",
        "seasonal_adjustment_short": "NSA",
        "last_updated": "2024-11-13 07:44:16-06",
        "popularity": 1,
        "group_popularity": 1
    },
    {
        "id": "CUURX200SS47015",
        "realtime_start": "2024-12-01",
        "realtime_end": "2024-12-01",
        "title": "Consumer Price Index for All Urban Consumers: Gasoline, Unleaded Midgrade in Midwest - Size Class B/C",
        "observation_start": "1997-12-01",
        "observation_end": "2024-10-01",
        "frequency": "Monthly",
        "frequency_short": "M",
        "units": "Index Dec 1997=100",
        "units_short": "Index Dec 1997=100",
        "seasonal_adjustment": "Not Seasonally Adjusted",
        "seasonal_adjustment_short": "NSA",
        "last_updated": "2024-11-13 07:45:12-06",
        "popularity": 0,
        "group_popularity": 0
    },
    {
        "id": "CUURX200SS47016",
        "realtime_start": "2024-12-01",
        "realtime_end": "2024-12-01",
        "title": "Consumer Price Index for All Urban Consumers: Gasoline, Unleaded Premium in Midwest - Size Class B/C",
        "observation_start": "1997-12-01",
        "observation_end": "2024-10-01",
        "frequency": "Monthly",
        "frequency_short": "M",
        "units": "Index Dec 1997=100",
        "units_short": "Index Dec 1997=100",
        "seasonal_adjustment": "Not Seasonally Adjusted",
        "seasonal_adjustment_short": "NSA",
        "last_updated": "2024-11-13 07:45:12-06",
        "popularity": 0,
        "group_popularity": 0
    },
    {
        "id": "CUUSX200SA0",
        "realtime_start": "2024-12-01",
        "realtime_end": "2024-12-01",
        "title": "Consumer Price Index for All Urban Consumers: All Items in Midwest - Size Class B/C",
        "observation_start": "1997-01-01",
        "observation_end": "2024-01-01",
        "frequency": "Semiannual",
        "frequency_short": "SA",
        "units": "Index Dec 1996=100",
        "units_short": "Index Dec 1996=100",
        "seasonal_adjustment": "Not Seasonally Adjusted",
        "seasonal_adjustment_short": "NSA",
        "last_updated": "2024-07-11 07:40:34-05",
        "popularity": 1,
        "group_popularity": 5
    },
    {
        "id": "CUUSX200SA0E",
        "realtime_start": "2024-12-01",
        "realtime_end": "2024-12-01",
        "title": "Consumer Price Index for All Urban Consumers: Energy in Midwest - Size Class B/C",
        "observation_start": "1998-01-01",
        "observation_end": "2024-01-01",
        "frequency": "Semiannual",
        "frequency_short": "SA",
        "units": "Index Dec 1997=100",
        "units_short": "Index Dec 1997=100",
        "seasonal_adjustment": "Not Seasonally Adjusted",
        "seasonal_adjustment_short": "NSA",
        "last_updated": "2024-07-11 07:42:00-05",
        "popularity": 1,
        "group_popularity": 1
    },
    {
        "id": "CUUSX200SA0L1E",
        "realtime_start": "2024-12-01",
        "realtime_end": "2024-12-01",
        "title": "Consumer Price Index for All Urban Consumers: All Items Less Food and Energy in Midwest - Size Class B/C",
        "observation_start": "1998-01-01",
        "observation_end": "2024-01-01",
        "frequency": "Semiannual",
        "frequency_short": "SA",
        "units": "Index Dec 1997=100",
        "units_short": "Index Dec 1997=100",
        "seasonal_adjustment": "Not Seasonally Adjusted",
        "seasonal_adjustment_short": "NSA",
        "last_updated": "2024-07-11 07:42:59-05",
        "popularity": 0,
        "group_popularity": 1
    },
    {
        "id": "CUUSX200SA0L2",
        "realtime_start": "2024-12-01",
        "realtime_end": "2024-12-01",
        "title": "Consumer Price Index for All Urban Consumers: All Items Less Shelter in Midwest - Size Class B/C",
        "observation_start": "1998-01-01",
        "observation_end": "2024-01-01",
        "frequency": "Semiannual",
        "frequency_short": "SA",
        "units": "Index Dec 1997=100",
        "units_short": "Index Dec 1997=100",
        "seasonal_adjustment": "Not Seasonally Adjusted",
        "seasonal_adjustment_short": "NSA",
        "last_updated": "2024-07-11 07:42:00-05",
        "popularity": 1,
        "group_popularity": 1
    },
    {
        "id": "CUUSX200SA0L5",
        "realtime_start": "2024-12-01",
        "realtime_end": "2024-12-01",
        "title": "Consumer Price Index for All Urban Consumers: All Items Less Medical Care in Midwest - Size Class B/C",
        "observation_start": "1998-01-01",
        "observation_end": "2024-01-01",
        "frequency": "Semiannual",
        "frequency_short": "SA",
        "units": "Index Dec 1997=100",
        "units_short": "Index Dec 1997=100",
        "seasonal_adjustment": "Not Seasonally Adjusted",
        "seasonal_adjustment_short": "NSA",
        "last_updated": "2024-07-11 07:42:59-05",
        "popularity": 0,
        "group_popularity": 1
    },
    {
        "id": "CUUSX200SA0LE",
        "realtime_start": "2024-12-01",
        "realtime_end": "2024-12-01",
        "title": "Consumer Price Index for All Urban Consumers: All Items Less Energy in Midwest - Size Class B/C",
        "observation_start": "1998-01-01",
        "observation_end": "2024-01-01",
        "frequency": "Semiannual",
        "frequency_short": "SA",
        "units": "Index Dec 1997=100",
        "units_short": "Index Dec 1997=100",
        "seasonal_adjustment": "Not Seasonally Adjusted",
        "seasonal_adjustment_short": "NSA",
        "last_updated": "2024-07-11 07:42:59-05",
        "popularity": 0,
        "group_popularity": 1
    },
    {
        "id": "CUUSX200SAA",
        "realtime_start": "2024-12-01",
        "realtime_end": "2024-12-01",
        "title": "Consumer Price Index for All Urban Consumers: Apparel in Midwest - Size Class B/C",
        "observation_start": "1998-01-01",
        "observation_end": "2024-01-01",
        "frequency": "Semiannual",
        "frequency_short": "SA",
        "units": "Index Dec 1997=100",
        "units_short": "Index Dec 1997=100",
        "seasonal_adjustment": "Not Seasonally Adjusted",
        "seasonal_adjustment_short": "NSA",
        "last_updated": "2024-07-11 07:42:59-05",
        "popularity": 0,
        "group_popularity": 0
    },
    {
        "id": "CUUSX200SAC",
        "realtime_start": "2024-12-01",
        "realtime_end": "2024-12-01",
        "title": "Consumer Price Index for All Urban Consumers: Commodities in Midwest - Size Class B/C",
        "observation_start": "1998-01-01",
        "observation_end": "2024-01-01",
        "frequency": "Semiannual",
        "frequency_short": "SA",
        "units": "Index Dec 1997=100",
        "units_short": "Index Dec 1997=100",
        "seasonal_adjustment": "Not Seasonally Adjusted",
        "seasonal_adjustment_short": "NSA",
        "last_updated": "2024-07-11 07:42:59-05",
        "popularity": 0,
        "group_popularity": 0
    },
    {
        "id": "CUUSX200SACL1",
        "realtime_start": "2024-12-01",
        "realtime_end": "2024-12-01",
        "title": "Consumer Price Index for All Urban Consumers: Commodities Less Food in Midwest - Size Class B/C",
        "observation_start": "1998-01-01",
        "observation_end": "2024-01-01",
        "frequency": "Semiannual",
        "frequency_short": "SA",
        "units": "Index Dec 1997=100",
        "units_short": "Index Dec 1997=100",
        "seasonal_adjustment": "Not Seasonally Adjusted",
        "seasonal_adjustment_short": "NSA",
        "last_updated": "2024-07-11 07:42:59-05",
        "popularity": 0,
        "group_popularity": 0
    },
    {
        "id": "CUUSX200SACL11",
        "realtime_start": "2024-12-01",
        "realtime_end": "2024-12-01",
        "title": "Consumer Price Index for All Urban Consumers: Commodities Less Food and Beverages in Midwest - Size Class B/C",
        "observation_start": "1998-01-01",
        "observation_end": "2024-01-01",
        "frequency": "Semiannual",
        "frequency_short": "SA",
        "units": "Index Dec 1997=100",
        "units_short": "Index Dec 1997=100",
        "seasonal_adjustment": "Not Seasonally Adjusted",
        "seasonal_adjustment_short": "NSA",
        "last_updated": "2024-07-11 07:42:59-05",
        "popularity": 0,
        "group_popularity": 0
    },
    {
        "id": "CUUSX200SAD",
        "realtime_start": "2024-12-01",
        "realtime_end": "2024-12-01",
        "title": "Consumer Price Index for All Urban Consumers: Durables in Midwest - Size Class B/C",
        "observation_start": "1998-01-01",
        "observation_end": "2024-01-01",
        "frequency": "Semiannual",
        "frequency_short": "SA",
        "units": "Index Dec 1997=100",
        "units_short": "Index Dec 1997=100",
        "seasonal_adjustment": "Not Seasonally Adjusted",
        "seasonal_adjustment_short": "NSA",
        "last_updated": "2024-07-11 07:42:59-05",
        "popularity": 0,
        "group_popularity": 0
    },
    {
        "id": "CUUSX200SAE",
        "realtime_start": "2024-12-01",
        "realtime_end": "2024-12-01",
        "title": "Consumer Price Index for All Urban Consumers: Education and Communication in Midwest - Size Class B/C",
        "observation_start": "1998-01-01",
        "observation_end": "2024-01-01",
        "frequency": "Semiannual",
        "frequency_short": "SA",
        "units": "Index Dec 1997=100",
        "units_short": "Index Dec 1997=100",
        "seasonal_adjustment": "Not Seasonally Adjusted",
        "seasonal_adjustment_short": "NSA",
        "last_updated": "2024-07-11 07:42:00-05",
        "popularity": 1,
        "group_popularity": 1
    },
    {
        "id": "CUUSX200SAEC",
        "realtime_start": "2024-12-01",
        "realtime_end": "2024-12-01",
        "title": "Consumer Price Index for All Urban Consumers: Education and Communication Commodities in Midwest - Size Class B/C",
        "observation_start": "2010-01-01",
        "observation_end": "2024-01-01",
        "frequency": "Semiannual",
        "frequency_short": "SA",
        "units": "Index Dec 2009=100",
        "units_short": "Index Dec 2009=100",
        "seasonal_adjustment": "Not Seasonally Adjusted",
        "seasonal_adjustment_short": "NSA",
        "last_updated": "2024-07-11 07:42:59-05",
        "popularity": 0,
        "group_popularity": 0
    },
    {
        "id": "CUUSX200SAES",
        "realtime_start": "2024-12-01",
        "realtime_end": "2024-12-01",
        "title": "Consumer Price Index for All Urban Consumers: Education and Communication Services in Midwest - Size Class B/C",
        "observation_start": "2010-01-01",
        "observation_end": "2024-01-01",
        "frequency": "Semiannual",
        "frequency_short": "SA",
        "units": "Index Dec 2009=100",
        "units_short": "Index Dec 2009=100",
        "seasonal_adjustment": "Not Seasonally Adjusted",
        "seasonal_adjustment_short": "NSA",
        "last_updated": "2024-07-11 07:42:58-05",
        "popularity": 0,
        "group_popularity": 0
    },
    {
        "id": "CUUSX200SAF",
        "realtime_start": "2024-12-01",
        "realtime_end": "2024-12-01",
        "title": "Consumer Price Index for All Urban Consumers: Food and Beverages in Midwest - Size Class B/C",
        "observation_start": "1998-01-01",
        "observation_end": "2024-01-01",
        "frequency": "Semiannual",
        "frequency_short": "SA",
        "units": "Index Dec 1997=100",
        "units_short": "Index Dec 1997=100",
        "seasonal_adjustment": "Not Seasonally Adjusted",
        "seasonal_adjustment_short": "NSA",
        "last_updated": "2024-07-11 07:42:00-05",
        "popularity": 1,
        "group_popularity": 1
    },
    {
        "id": "CUUSX200SAF1",
        "realtime_start": "2024-12-01",
        "realtime_end": "2024-12-01",
        "title": "Consumer Price Index for All Urban Consumers: Food in Midwest - Size Class B/C",
        "observation_start": "1998-01-01",
        "observation_end": "2024-01-01",
        "frequency": "Semiannual",
        "frequency_short": "SA",
        "units": "Index Dec 1997=100",
        "units_short": "Index Dec 1997=100",
        "seasonal_adjustment": "Not Seasonally Adjusted",
        "seasonal_adjustment_short": "NSA",
        "last_updated": "2024-07-11 07:42:00-05",
        "popularity": 1,
        "group_popularity": 1
    },
    {
        "id": "CUUSX200SAF11",
        "realtime_start": "2024-12-01",
        "realtime_end": "2024-12-01",
        "title": "Consumer Price Index for All Urban Consumers: Food at Home in Midwest - Size Class B/C",
        "observation_start": "1998-01-01",
        "observation_end": "2024-01-01",
        "frequency": "Semiannual",
        "frequency_short": "SA",
        "units": "Index Dec 1997=100",
        "units_short": "Index Dec 1997=100",
        "seasonal_adjustment": "Not Seasonally Adjusted",
        "seasonal_adjustment_short": "NSA",
        "last_updated": "2024-07-11 07:42:58-05",
        "popularity": 0,
        "group_popularity": 1
    },
    {
        "id": "CUUSX200SAF116",
        "realtime_start": "2024-12-01",
        "realtime_end": "2024-12-01",
        "title": "Consumer Price Index for All Urban Consumers: Alcoholic Beverages in Midwest - Size Class B/C",
        "observation_start": "1998-01-01",
        "observation_end": "2024-01-01",
        "frequency": "Semiannual",
        "frequency_short": "SA",
        "units": "Index Dec 1997=100",
        "units_short": "Index Dec 1997=100",
        "seasonal_adjustment": "Not Seasonally Adjusted",
        "seasonal_adjustment_short": "NSA",
        "last_updated": "2024-07-11 07:42:58-05",
        "popularity": 0,
        "group_popularity": 1
    },
    {
        "id": "CUUSX200SAG",
        "realtime_start": "2024-12-01",
        "realtime_end": "2024-12-01",
        "title": "Consumer Price Index for All Urban Consumers: Other Goods and Services in Midwest - Size Class B/C",
        "observation_start": "1998-01-01",
        "observation_end": "2024-01-01",
        "frequency": "Semiannual",
        "frequency_short": "SA",
        "units": "Index Dec 1997=100",
        "units_short": "Index Dec 1997=100",
        "seasonal_adjustment": "Not Seasonally Adjusted",
        "seasonal_adjustment_short": "NSA",
        "last_updated": "2024-07-11 07:42:58-05",
        "popularity": 0,
        "group_popularity": 0
    },
    {
        "id": "CUUSX200SAGC",
        "realtime_start": "2024-12-01",
        "realtime_end": "2024-12-01",
        "title": "Consumer Price Index for All Urban Consumers: Other Goods in Midwest - Size Class B/C",
        "observation_start": "2010-01-01",
        "observation_end": "2024-01-01",
        "frequency": "Semiannual",
        "frequency_short": "SA",
        "units": "Index Dec 2009=100",
        "units_short": "Index Dec 2009=100",
        "seasonal_adjustment": "Not Seasonally Adjusted",
        "seasonal_adjustment_short": "NSA",
        "last_updated": "2024-07-11 07:42:58-05",
        "popularity": 0,
        "group_popularity": 0
    },
    {
        "id": "CUUSX200SAGS",
        "realtime_start": "2024-12-01",
        "realtime_end": "2024-12-01",
        "title": "Consumer Price Index for All Urban Consumers: Other Personal Services in Midwest - Size Class B/C",
        "observation_start": "2010-01-01",
        "observation_end": "2024-01-01",
        "frequency": "Semiannual",
        "frequency_short": "SA",
        "units": "Index Dec 2009=100",
        "units_short": "Index Dec 2009=100",
        "seasonal_adjustment": "Not Seasonally Adjusted",
        "seasonal_adjustment_short": "NSA",
        "last_updated": "2024-07-11 07:42:58-05",
        "popularity": 0,
        "group_popularity": 0
    },
    {
        "id": "CUUSX200SAH",
        "realtime_start": "2024-12-01",
        "realtime_end": "2024-12-01",
        "title": "Consumer Price Index for All Urban Consumers: Housing in Midwest - Size Class B/C",
        "observation_start": "1998-01-01",
        "observation_end": "2024-01-01",
        "frequency": "Semiannual",
        "frequency_short": "SA",
        "units": "Index Dec 1997=100",
        "units_short": "Index Dec 1997=100",
        "seasonal_adjustment": "Not Seasonally Adjusted",
        "seasonal_adjustment_short": "NSA",
        "last_updated": "2024-07-11 07:42:58-05",
        "popularity": 0,
        "group_popularity": 1
    },
    {
        "id": "CUUSX200SAH1",
        "realtime_start": "2024-12-01",
        "realtime_end": "2024-12-01",
        "title": "Consumer Price Index for All Urban Consumers: Shelter in Midwest - Size Class B/C",
        "observation_start": "1998-01-01",
        "observation_end": "2024-01-01",
        "frequency": "Semiannual",
        "frequency_short": "SA",
        "units": "Index Dec 1997=100",
        "units_short": "Index Dec 1997=100",
        "seasonal_adjustment": "Not Seasonally Adjusted",
        "seasonal_adjustment_short": "NSA",
        "last_updated": "2024-07-11 07:43:13-05",
        "popularity": 0,
        "group_popularity": 1
    },
    {
        "id": "CUUSX200SAH2",
        "realtime_start": "2024-12-01",
        "realtime_end": "2024-12-01",
        "title": "Consumer Price Index for All Urban Consumers: Fuels and Utilities in Midwest - Size Class B/C",
        "observation_start": "1998-01-01",
        "observation_end": "2024-01-01",
        "frequency": "Semiannual",
        "frequency_short": "SA",
        "units": "Index Dec 1997=100",
        "units_short": "Index Dec 1997=100",
        "seasonal_adjustment": "Not Seasonally Adjusted",
        "seasonal_adjustment_short": "NSA",
        "last_updated": "2024-07-11 07:43:13-05",
        "popularity": 0,
        "group_popularity": 1
    },
    {
        "id": "CUUSX200SAH21",
        "realtime_start": "2024-12-01",
        "realtime_end": "2024-12-01",
        "title": "Consumer Price Index for All Urban Consumers: Household Energy in Midwest - Size Class B/C",
        "observation_start": "1998-01-01",
        "observation_end": "2024-01-01",
        "frequency": "Semiannual",
        "frequency_short": "SA",
        "units": "Index Dec 1997=100",
        "units_short": "Index Dec 1997=100",
        "seasonal_adjustment": "Not Seasonally Adjusted",
        "seasonal_adjustment_short": "NSA",
        "last_updated": "2024-07-11 07:43:13-05",
        "popularity": 0,
        "group_popularity": 0
    },
    {
        "id": "CUUSX200SAH3",
        "realtime_start": "2024-12-01",
        "realtime_end": "2024-12-01",
        "title": "Consumer Price Index for All Urban Consumers: Household Furnishings and Operations in Midwest - Size Class B/C",
        "observation_start": "1998-01-01",
        "observation_end": "2024-01-01",
        "frequency": "Semiannual",
        "frequency_short": "SA",
        "units": "Index Dec 1997=100",
        "units_short": "Index Dec 1997=100",
        "seasonal_adjustment": "Not Seasonally Adjusted",
        "seasonal_adjustment_short": "NSA",
        "last_updated": "2024-07-11 07:43:13-05",
        "popularity": 0,
        "group_popularity": 0
    },
    {
        "id": "CUUSX200SAH31",
        "realtime_start": "2024-12-01",
        "realtime_end": "2024-12-01",
        "title": "Consumer Price Index for All Urban Consumers: Household Furnishings and Supplies in Midwest - Size Class B/C",
        "observation_start": "2010-01-01",
        "observation_end": "2024-01-01",
        "frequency": "Semiannual",
        "frequency_short": "SA",
        "units": "Index Dec 2009=100",
        "units_short": "Index Dec 2009=100",
        "seasonal_adjustment": "Not Seasonally Adjusted",
        "seasonal_adjustment_short": "NSA",
        "last_updated": "2024-07-11 07:43:13-05",
        "popularity": 0,
        "group_popularity": 1
    },
    {
        "id": "CUUSX200SAM",
        "realtime_start": "2024-12-01",
        "realtime_end": "2024-12-01",
        "title": "Consumer Price Index for All Urban Consumers: Medical Care in Midwest - Size Class B/C",
        "observation_start": "1998-01-01",
        "observation_end": "2024-01-01",
        "frequency": "Semiannual",
        "frequency_short": "SA",
        "units": "Index Dec 1997=100",
        "units_short": "Index Dec 1997=100",
        "seasonal_adjustment": "Not Seasonally Adjusted",
        "seasonal_adjustment_short": "NSA",
        "last_updated": "2024-07-11 07:43:12-05",
        "popularity": 0,
        "group_popularity": 1
    },
    {
        "id": "CUUSX200SAN",
        "realtime_start": "2024-12-01",
        "realtime_end": "2024-12-01",
        "title": "Consumer Price Index for All Urban Consumers: Nondurables in Midwest - Size Class B/C",
        "observation_start": "1998-01-01",
        "observation_end": "2024-01-01",
        "frequency": "Semiannual",
        "frequency_short": "SA",
        "units": "Index Dec 1997=100",
        "units_short": "Index Dec 1997=100",
        "seasonal_adjustment": "Not Seasonally Adjusted",
        "seasonal_adjustment_short": "NSA",
        "last_updated": "2024-07-11 07:43:12-05",
        "popularity": 0,
        "group_popularity": 0
    },
    {
        "id": "CUUSX200SANL1",
        "realtime_start": "2024-12-01",
        "realtime_end": "2024-12-01",
        "title": "Consumer Price Index for All Urban Consumers: Nondurables Less Food in Midwest - Size Class B/C",
        "observation_start": "1998-01-01",
        "observation_end": "2024-01-01",
        "frequency": "Semiannual",
        "frequency_short": "SA",
        "units": "Index Dec 1997=100",
        "units_short": "Index Dec 1997=100",
        "seasonal_adjustment": "Not Seasonally Adjusted",
        "seasonal_adjustment_short": "NSA",
        "last_updated": "2024-07-11 07:43:12-05",
        "popularity": 0,
        "group_popularity": 1
    },
    {
        "id": "CUUSX200SANL11",
        "realtime_start": "2024-12-01",
        "realtime_end": "2024-12-01",
        "title": "Consumer Price Index for All Urban Consumers: Nondurables Less Food and Beverages in Midwest - Size Class B/C",
        "observation_start": "1998-01-01",
        "observation_end": "2024-01-01",
        "frequency": "Semiannual",
        "frequency_short": "SA",
        "units": "Index Dec 1997=100",
        "units_short": "Index Dec 1997=100",
        "seasonal_adjustment": "Not Seasonally Adjusted",
        "seasonal_adjustment_short": "NSA",
        "last_updated": "2024-07-11 07:43:12-05",
        "popularity": 0,
        "group_popularity": 0
    },
    {
        "id": "CUUSX200SAR",
        "realtime_start": "2024-12-01",
        "realtime_end": "2024-12-01",
        "title": "Consumer Price Index for All Urban Consumers: Recreation in Midwest - Size Class B/C",
        "observation_start": "1998-01-01",
        "observation_end": "2024-01-01",
        "frequency": "Semiannual",
        "frequency_short": "SA",
        "units": "Index Dec 1997=100",
        "units_short": "Index Dec 1997=100",
        "seasonal_adjustment": "Not Seasonally Adjusted",
        "seasonal_adjustment_short": "NSA",
        "last_updated": "2024-07-11 07:43:12-05",
        "popularity": 0,
        "group_popularity": 1
    },
    {
        "id": "CUUSX200SAS",
        "realtime_start": "2024-12-01",
        "realtime_end": "2024-12-01",
        "title": "Consumer Price Index for All Urban Consumers: Services in Midwest - Size Class B/C",
        "observation_start": "1998-01-01",
        "observation_end": "2024-01-01",
        "frequency": "Semiannual",
        "frequency_short": "SA",
        "units": "Index Dec 1997=100",
        "units_short": "Index Dec 1997=100",
        "seasonal_adjustment": "Not Seasonally Adjusted",
        "seasonal_adjustment_short": "NSA",
        "last_updated": "2024-07-11 07:43:12-05",
        "popularity": 0,
        "group_popularity": 0
    },
    {
        "id": "CUUSX200SASL2RS",
        "realtime_start": "2024-12-01",
        "realtime_end": "2024-12-01",
        "title": "Consumer Price Index for All Urban Consumers: Services Less Rent of Shelter in Midwest - Size Class B/C",
        "observation_start": "1998-01-01",
        "observation_end": "2024-01-01",
        "frequency": "Semiannual",
        "frequency_short": "SA",
        "units": "Index Dec 1997=100",
        "units_short": "Index Dec 1997=100",
        "seasonal_adjustment": "Not Seasonally Adjusted",
        "seasonal_adjustment_short": "NSA",
        "last_updated": "2024-07-11 07:42:00-05",
        "popularity": 1,
        "group_popularity": 1
    },
    {
        "id": "CUUSX200SASL5",
        "realtime_start": "2024-12-01",
        "realtime_end": "2024-12-01",
        "title": "Consumer Price Index for All Urban Consumers: Services Less Medical Care Services in Midwest - Size Class B/C",
        "observation_start": "1998-01-01",
        "observation_end": "2024-01-01",
        "frequency": "Semiannual",
        "frequency_short": "SA",
        "units": "Index Dec 1997=100",
        "units_short": "Index Dec 1997=100",
        "seasonal_adjustment": "Not Seasonally Adjusted",
        "seasonal_adjustment_short": "NSA",
        "last_updated": "2024-07-11 07:42:00-05",
        "popularity": 1,
        "group_popularity": 1
    },
    {
        "id": "CUUSX200SAT",
        "realtime_start": "2024-12-01",
        "realtime_end": "2024-12-01",
        "title": "Consumer Price Index for All Urban Consumers: Transportation in Midwest - Size Class B/C",
        "observation_start": "1998-01-01",
        "observation_end": "2024-01-01",
        "frequency": "Semiannual",
        "frequency_short": "SA",
        "units": "Index Dec 1997=100",
        "units_short": "Index Dec 1997=100",
        "seasonal_adjustment": "Not Seasonally Adjusted",
        "seasonal_adjustment_short": "NSA",
        "last_updated": "2024-07-11 07:43:12-05",
        "popularity": 0,
        "group_popularity": 0
    },
    {
        "id": "CUUSX200SAT1",
        "realtime_start": "2024-12-01",
        "realtime_end": "2024-12-01",
        "title": "Consumer Price Index for All Urban Consumers: Private Transportation in Midwest - Size Class B/C",
        "observation_start": "1998-01-01",
        "observation_end": "2024-01-01",
        "frequency": "Semiannual",
        "frequency_short": "SA",
        "units": "Index Dec 1997=100",
        "units_short": "Index Dec 1997=100",
        "seasonal_adjustment": "Not Seasonally Adjusted",
        "seasonal_adjustment_short": "NSA",
        "last_updated": "2024-07-11 07:43:12-05",
        "popularity": 0,
        "group_popularity": 0
    },
    {
        "id": "CUUSX200SATCLTB",
        "realtime_start": "2024-12-01",
        "realtime_end": "2024-12-01",
        "title": "Consumer Price Index for All Urban Consumers: Transportation Commodities Less Motor Fuel in Midwest - Size Class B/C",
        "observation_start": "2010-01-01",
        "observation_end": "2024-01-01",
        "frequency": "Semiannual",
        "frequency_short": "SA",
        "units": "Index Dec 2009=100",
        "units_short": "Index Dec 2009=100",
        "seasonal_adjustment": "Not Seasonally Adjusted",
        "seasonal_adjustment_short": "NSA",
        "last_updated": "2024-07-11 07:43:12-05",
        "popularity": 0,
        "group_popularity": 1
    },
    {
        "id": "CUUSX200SEFV",
        "realtime_start": "2024-12-01",
        "realtime_end": "2024-12-01",
        "title": "Consumer Price Index for All Urban Consumers: Food Away from Home in Midwest - Size Class B/C",
        "observation_start": "1998-01-01",
        "observation_end": "2024-01-01",
        "frequency": "Semiannual",
        "frequency_short": "SA",
        "units": "Index Dec 1997=100",
        "units_short": "Index Dec 1997=100",
        "seasonal_adjustment": "Not Seasonally Adjusted",
        "seasonal_adjustment_short": "NSA",
        "last_updated": "2024-07-11 07:43:12-05",
        "popularity": 0,
        "group_popularity": 0
    },
    {
        "id": "CUUSX200SEHA",
        "realtime_start": "2024-12-01",
        "realtime_end": "2024-12-01",
        "title": "Consumer Price Index for All Urban Consumers: Rent of Primary Residence in Midwest - Size Class B/C",
        "observation_start": "1998-01-01",
        "observation_end": "2024-01-01",
        "frequency": "Semiannual",
        "frequency_short": "SA",
        "units": "Index Dec 1997=100",
        "units_short": "Index Dec 1997=100",
        "seasonal_adjustment": "Not Seasonally Adjusted",
        "seasonal_adjustment_short": "NSA",
        "last_updated": "2024-07-11 07:43:12-05",
        "popularity": 0,
        "group_popularity": 1
    },
    {
        "id": "CUUSX200SEHC",
        "realtime_start": "2024-12-01",
        "realtime_end": "2024-12-01",
        "title": "Consumer Price Index for All Urban Consumers: Owners' Equivalent Rent of Residences in Midwest - Size Class B/C",
        "observation_start": "1998-01-01",
        "observation_end": "2024-01-01",
        "frequency": "Semiannual",
        "frequency_short": "SA",
        "units": "Index Dec 1997=100",
        "units_short": "Index Dec 1997=100",
        "seasonal_adjustment": "Not Seasonally Adjusted",
        "seasonal_adjustment_short": "NSA",
        "last_updated": "2024-07-11 07:42:00-05",
        "popularity": 1,
        "group_popularity": 1
    },
    {
        "id": "CUUSX200SEHC01",
        "realtime_start": "2024-12-01",
        "realtime_end": "2024-12-01",
        "title": "Consumer Price Index for All Urban Consumers: Owners' Equivalent Rent of Primary Residence in Midwest - Size Class B/C",
        "observation_start": "1998-01-01",
        "observation_end": "2024-01-01",
        "frequency": "Semiannual",
        "frequency_short": "SA",
        "units": "Index Dec 1997=100",
        "units_short": "Index Dec 1997=100",
        "seasonal_adjustment": "Not Seasonally Adjusted",
        "seasonal_adjustment_short": "NSA",
        "last_updated": "2024-07-11 07:43:12-05",
        "popularity": 0,
        "group_popularity": 0
    },
    {
        "id": "CUUSX200SEHF",
        "realtime_start": "2024-12-01",
        "realtime_end": "2024-12-01",
        "title": "Consumer Price Index for All Urban Consumers: Energy Services in Midwest - Size Class B/C",
        "observation_start": "1998-01-01",
        "observation_end": "2024-01-01",
        "frequency": "Semiannual",
        "frequency_short": "SA",
        "units": "Index Dec 1997=100",
        "units_short": "Index Dec 1997=100",
        "seasonal_adjustment": "Not Seasonally Adjusted",
        "seasonal_adjustment_short": "NSA",
        "last_updated": "2024-07-11 07:43:12-05",
        "popularity": 0,
        "group_popularity": 0
    },
    {
        "id": "CUUSX200SEHF01",
        "realtime_start": "2024-12-01",
        "realtime_end": "2024-12-01",
        "title": "Consumer Price Index for All Urban Consumers: Electricity in Midwest - Size Class B/C",
        "observation_start": "1998-01-01",
        "observation_end": "2024-01-01",
        "frequency": "Semiannual",
        "frequency_short": "SA",
        "units": "Index Dec 1997=100",
        "units_short": "Index Dec 1997=100",
        "seasonal_adjustment": "Not Seasonally Adjusted",
        "seasonal_adjustment_short": "NSA",
        "last_updated": "2024-07-11 07:42:00-05",
        "popularity": 1,
        "group_popularity": 1
    },
    {
        "id": "CUUSX200SEHF02",
        "realtime_start": "2024-12-01",
        "realtime_end": "2024-12-01",
        "title": "Consumer Price Index for All Urban Consumers: Utility (Piped) Gas Service in Midwest - Size Class B/C",
        "observation_start": "1998-01-01",
        "observation_end": "2024-01-01",
        "frequency": "Semiannual",
        "frequency_short": "SA",
        "units": "Index Dec 1997=100",
        "units_short": "Index Dec 1997=100",
        "seasonal_adjustment": "Not Seasonally Adjusted",
        "seasonal_adjustment_short": "NSA",
        "last_updated": "2024-07-11 07:43:12-05",
        "popularity": 0,
        "group_popularity": 0
    },
    {
        "id": "CUUSX200SETB",
        "realtime_start": "2024-12-01",
        "realtime_end": "2024-12-01",
        "title": "Consumer Price Index for All Urban Consumers: Motor Fuel in Midwest - Size Class B/C",
        "observation_start": "1998-01-01",
        "observation_end": "2024-01-01",
        "frequency": "Semiannual",
        "frequency_short": "SA",
        "units": "Index Dec 1997=100",
        "units_short": "Index Dec 1997=100",
        "seasonal_adjustment": "Not Seasonally Adjusted",
        "seasonal_adjustment_short": "NSA",
        "last_updated": "2024-07-11 07:42:00-05",
        "popularity": 1,
        "group_popularity": 1
    },
    {
        "id": "CUUSX200SETB01",
        "realtime_start": "2024-12-01",
        "realtime_end": "2024-12-01",
        "title": "Consumer Price Index for All Urban Consumers: Gasoline (All Types) in Midwest - Size Class B/C",
        "observation_start": "1998-01-01",
        "observation_end": "2024-01-01",
        "frequency": "Semiannual",
        "frequency_short": "SA",
        "units": "Index Dec 1997=100",
        "units_short": "Index Dec 1997=100",
        "seasonal_adjustment": "Not Seasonally Adjusted",
        "seasonal_adjustment_short": "NSA",
        "last_updated": "2024-07-11 07:42:00-05",
        "popularity": 1,
        "group_popularity": 1
    },
    {
        "id": "CUUSX200SS47014",
        "realtime_start": "2024-12-01",
        "realtime_end": "2024-12-01",
        "title": "Consumer Price Index for All Urban Consumers: Gasoline, Unleaded Regular in Midwest - Size Class B/C",
        "observation_start": "1998-01-01",
        "observation_end": "2024-01-01",
        "frequency": "Semiannual",
        "frequency_short": "SA",
        "units": "Index Dec 1997=100",
        "units_short": "Index Dec 1997=100",
        "seasonal_adjustment": "Not Seasonally Adjusted",
        "seasonal_adjustment_short": "NSA",
        "last_updated": "2024-07-11 07:41:59-05",
        "popularity": 1,
        "group_popularity": 1
    },
    {
        "id": "CUUSX200SS47015",
        "realtime_start": "2024-12-01",
        "realtime_end": "2024-12-01",
        "title": "Consumer Price Index for All Urban Consumers: Gasoline, Unleaded Midgrade in Midwest - Size Class B/C",
        "observation_start": "1998-01-01",
        "observation_end": "2024-01-01",
        "frequency": "Semiannual",
        "frequency_short": "SA",
        "units": "Index Dec 1997=100",
        "units_short": "Index Dec 1997=100",
        "seasonal_adjustment": "Not Seasonally Adjusted",
        "seasonal_adjustment_short": "NSA",
        "last_updated": "2024-07-11 07:43:12-05",
        "popularity": 0,
        "group_popularity": 0
    },
    {
        "id": "CUUSX200SS47016",
        "realtime_start": "2024-12-01",
        "realtime_end": "2024-12-01",
        "title": "Consumer Price Index for All Urban Consumers: Gasoline, Unleaded Premium in Midwest - Size Class B/C",
        "observation_start": "1998-01-01",
        "observation_end": "2024-01-01",
        "frequency": "Semiannual",
        "frequency_short": "SA",
        "units": "Index Dec 1997=100",
        "units_short": "Index Dec 1997=100",
        "seasonal_adjustment": "Not Seasonally Adjusted",
        "seasonal_adjustment_short": "NSA",
        "last_updated": "2024-07-11 07:43:12-05",
        "popularity": 0,
        "group_popularity": 0
    }
]